nimbus_scrapy/__init__.py
nimbus_scrapy/exceptions.py
nimbus_scrapy/item.py
nimbus_scrapy/models.py
nimbus_scrapy/settings.py
nimbus_scrapy/test.py
nimbus_scrapy/utils.py
nimbus_scrapy/callback/__init__.py
nimbus_scrapy/callback/db.py
nimbus_scrapy/callback/item.py
nimbus_scrapy/data/__init__.py
nimbus_scrapy/data/db.py
nimbus_scrapy/data/redis.py
nimbus_scrapy/extensions/__init__.py
nimbus_scrapy/extensions/spend.py
nimbus_scrapy/loader/__init__.py
nimbus_scrapy/loader/processors.py
nimbus_scrapy/middlewares/__init__.py
nimbus_scrapy/middlewares/deltafetch.py
nimbus_scrapy/middlewares/httpproxy.py
nimbus_scrapy/middlewares/httpproxys.py
nimbus_scrapy/middlewares/retry.py
nimbus_scrapy/middlewares/useragent.py
nimbus_scrapy/pipelines/__init__.py
nimbus_scrapy/pipelines/callback.py
nimbus_scrapy/pipelines/files.py
nimbus_scrapy/pipelines/images.py
nimbus_scrapy/pipelines/item.py
nimbus_scrapy/pipelines/mq.py
nimbus_scrapy/spiders/__init__.py
nimbus_scrapy/spiders/base.py
nimbus_scrapy/spiders/crawl.py
nimbus_scrapy/spiders/crawler.py
nimbus_scrapy/spiders/mixin.py
nimbus_scrapy/spiders/mixins.py
nimbus_scrapy-4.1.2.dist-info/LICENSE.md
nimbus_scrapy-4.1.2.dist-info/METADATA
nimbus_scrapy-4.1.2.dist-info/WHEEL
nimbus_scrapy-4.1.2.dist-info/top_level.txt
nimbus_scrapy-4.1.2.dist-info/RECORD
