Metadata-Version: 2.1
Name: nimbus-scrapy
Version: 4.1.2
Summary: nimbus_scrapy
Home-page: https://github.com/williamren
Author: william
Author-email: william.ren@live.cn
License: Apache License 2.0
Keywords: nimbus_scrapy,nimbus,scrapy,rabbitmq
Platform: Any
Classifier: Development Status :: 5 - Production/Stable
Classifier: Intended Audience :: Developers
Classifier: License :: OSI Approved :: Apache Software License
Classifier: Operating System :: MacOS :: MacOS X
Classifier: Operating System :: Microsoft :: Windows
Classifier: Operating System :: POSIX
Classifier: Programming Language :: Python
Classifier: Programming Language :: Python :: 2.7
Classifier: Programming Language :: Python :: 3
Classifier: Programming Language :: Python :: 3.3
Classifier: Programming Language :: Python :: 3.4
Classifier: Programming Language :: Python :: 3.5
Classifier: Programming Language :: Python :: 3.6
Classifier: Programming Language :: Python :: 3.7
Classifier: Topic :: Internet :: WWW/HTTP
Classifier: Environment :: Web Environment
Classifier: Framework :: Django
Classifier: Framework :: Django :: 1.8
Classifier: Framework :: Django :: 1.9
Classifier: Framework :: Django :: 1.10
Classifier: Framework :: Django :: 1.11
Requires-Dist: Scrapy (>=1.0.0)
Requires-Dist: SQLAlchemy (>=1.0.0)
Requires-Dist: selenium (>=3.0.0)
Requires-Dist: redis (>=2.0.0)
Requires-Dist: pymongo (>=3.0.0)
Requires-Dist: dateutils (>=0.6.6)
Requires-Dist: python-dateutil (>=2.6.1)
Requires-Dist: beautifulsoup4 (>=4.3.1)
Requires-Dist: zhon (>=1.1.5)
Requires-Dist: nimbus-utils (>=0.3.1)
Requires-Dist: Pillow (>=5.0.0)
Requires-Dist: crochet (>=1.9.0)
Requires-Dist: six
